tensorflow_serving/__init__.py
tensorflow_serving/apis/__init__.py
tensorflow_serving/apis/classification_pb2.py
tensorflow_serving/apis/get_model_metadata_pb2.py
tensorflow_serving/apis/inference_pb2.py
tensorflow_serving/apis/input_pb2.py
tensorflow_serving/apis/model_pb2.py
tensorflow_serving/apis/predict_pb2.py
tensorflow_serving/apis/prediction_service_pb2.py
tensorflow_serving/apis/prediction_service_pb2_grpc.py
tensorflow_serving/apis/regression_pb2.py
tensorflowservingclient-0.5.1.post2.dist-info/DESCRIPTION.rst
tensorflowservingclient-0.5.1.post2.dist-info/METADATA
tensorflowservingclient-0.5.1.post2.dist-info/RECORD
tensorflowservingclient-0.5.1.post2.dist-info/WHEEL
tensorflowservingclient-0.5.1.post2.dist-info/metadata.json
tensorflowservingclient-0.5.1.post2.dist-info/top_level.txt
