Metadata-Version: 2.0
Name: tensorflowservingclient
Version: 0.5.1.post2
Summary: Prebuilt tensorflow serving client
Home-page: https://github.com/yesup/tensorflow-serving-client-python
Author: Jeff Ye
Author-email: jeffye@yesup.com
License: Apache 2.0
Platform: UNKNOWN
Requires-Dist: grpcio
Requires-Dist: tensorflow
